Workbook

Sheet 📋 RAID Summary
A1: I-PROPERTY · PROJECT RAID LOG
A2: Meridian Commercial Properties · Rental Property Operations Platform · Project Level · Last Updated: April 2025
A5: Project Name | C5: I-Property
A6: Product | C6: Rental Property Operations Platform
A7: Version | C7: 1.0
A8: Status | C8: Active — Phase 1 In Progress
A9: Product Owner | C9: VP of Property Operations
A10: Prepared By | C10: Director of Product, Technology Division
A11: Date | C11: April 2025
A13: RAID ITEM SUMMARY · All counts are live formulas — update automatically when items are added or status changes
A14: RISKS | C14: ACTIONS | E14: ISSUES | G14: DECISIONS
A15: =COUNTA('🔴 Risks'!A6:A500) -> 14 | C15: =COUNTA('🟡 Actions'!A6:A500) -> 17 | E15: =COUNTA('🟠 Issues'!A6:A500) -> 11 | G15: =COUNTA('🔵 Decisions'!A6:A500) -> 12
A16: ="Open: "&TEXT(COUNTIF('🔴 Risks'!I6:I500,"Open"),"0") -> Open: 0 | C16: ="Open: "&TEXT(COUNTIF('🟡 Actions'!H6:H500,"Open"),"0") -> Open: 0 | E16: ="Open: "&TEXT(COUNTIF('🟠 Issues'!G6:G500,"Open"),"0") -> Open: 0 | G16: ="Pending: "&TEXT(COUNTIF('🔵 Decisions'!F6:F500,"PENDING*"),"0") -> Pending: 12
A17: =TEXT(COUNTIF('🔴 Risks'!H6:H500,"Critical"),"0")&" Critical" -> 0 Critical | C17: =TEXT(COUNTIF('🟡 Actions'!G6:G500,"Critical"),"0")&" Critical" -> 0 Critical | E17: =TEXT(COUNTIF('🟠 Issues'!F6:F500,"Critical"),"0")&" Critical" -> 0 Critical | G17: =TEXT(COUNTA('🔵 Decisions'!A6:A500)-COUNTIF('🔵 Decisions'!F6:F500,"PENDING*"),"0")&" Decided" -> 0 Decided
A18: → Sheet: 🔴 Risks | C18: → Sheet: 🟡 Actions | E18: → Sheet: 🟠 Issues | G18: → Sheet: 🔵 Decisions
A20: STATUS BREAKDOWN · Live formula counts by status across all RAID sheets
A21: Status | B21: Risks | C21: Actions | D21: Issues | E21: Decisions | F21: Total
A22: Open | B22: =COUNTIF('🔴 Risks'!I6:I500,"Open") -> 0 | C22: =COUNTIF('🟡 Actions'!H6:H500,"Open") -> 0 | D22: =COUNTIF('🟠 Issues'!G6:G500,"Open") -> 0 | E22: =COUNTIF('🔵 Decisions'!F6:F500,"PENDING*") -> 12 | F22: =IFERROR(COUNTIF('🔴 Risks'!I6:I500,"Open"),0)+IFERROR(COUNTIF('🟡 Actions'!H6:H500,"Open"),0)+IFERROR(COUNTIF('🟠 Issues'!G6:G500,"Open"),0)+IFERROR(COUNTIF('🔵 Decisions'!F6:F500,"PENDING*"),0) -> 12
A23: In Progress | B23: =COUNTIF('🔴 Risks'!I6:I500,"In Progress") -> 0 | C23: =COUNTIF('🟡 Actions'!H6:H500,"In Progress") -> 0 | D23: =COUNTIF('🟠 Issues'!G6:G500,"In Progress") -> 0 | E23: =0 -> 0 | F23: =IFERROR(COUNTIF('🔴 Risks'!I6:I500,"In Progress"),0)+IFERROR(COUNTIF('🟡 Actions'!H6:H500,"In Progress"),0)+IFERROR(COUNTIF('🟠 Issues'!G6:G500,"In Progress"),0)+IFERROR(0,0) -> 0
A24: Monitoring | B24: =COUNTIF('🔴 Risks'!I6:I500,"Monitoring") -> 0 | C24: =COUNTIF('🟡 Actions'!H6:H500,"Monitoring") -> 0 | D24: =COUNTIF('🟠 Issues'!G6:G500,"Monitoring") -> 0 | E24: =0 -> 0 | F24: =IFERROR(COUNTIF('🔴 Risks'!I6:I500,"Monitoring"),0)+IFERROR(COUNTIF('🟡 Actions'!H6:H500,"Monitoring"),0)+IFERROR(COUNTIF('🟠 Issues'!G6:G500,"Monitoring"),0)+IFERROR(0,0) -> 0
A25: Closed | B25: =COUNTIF('🔴 Risks'!I6:I500,"Closed") -> 0 | C25: =COUNTIF('🟡 Actions'!H6:H500,"Closed") -> 0 | D25: =COUNTIF('🟠 Issues'!G6:G500,"Closed") -> 0 | E25: =COUNTA('🔵 Decisions'!A6:A500)-COUNTIF('🔵 Decisions'!F6:F500,"PENDING*") -> 0 | F25: =IFERROR(COUNTIF('🔴 Risks'!I6:I500,"Closed"),0)+IFERROR(COUNTIF('🟡 Actions'!H6:H500,"Closed"),0)+IFERROR(COUNTIF('🟠 Issues'!G6:G500,"Closed"),0)+IFERROR(COUNTA('🔵 Decisions'!A6:A500)-COUNTIF('🔵 Decisions'!F6:F500,"PENDING*"),0) -> 0
A26: Escalated | B26: =COUNTIF('🔴 Risks'!I6:I500,"Escalated") -> 0 | C26: =COUNTIF('🟡 Actions'!H6:H500,"Escalated") -> 0 | D26: =COUNTIF('🟠 Issues'!G6:G500,"Escalated") -> 0 | E26: =0 -> 0 | F26: =IFERROR(COUNTIF('🔴 Risks'!I6:I500,"Escalated"),0)+IFERROR(COUNTIF('🟡 Actions'!H6:H500,"Escalated"),0)+IFERROR(COUNTIF('🟠 Issues'!G6:G500,"Escalated"),0)+IFERROR(0,0) -> 0
A27: Resolved | B27: =COUNTIF('🔴 Risks'!I6:I500,"Resolved") -> 0 | C27: =COUNTIF('🟡 Actions'!H6:H500,"Resolved") -> 0 | D27: =COUNTIF('🟠 Issues'!G6:G500,"Resolved") -> 0 | E27: =0 -> 0 | F27: =IFERROR(COUNTIF('🔴 Risks'!I6:I500,"Resolved"),0)+IFERROR(COUNTIF('🟡 Actions'!H6:H500,"Resolved"),0)+IFERROR(COUNTIF('🟠 Issues'!G6:G500,"Resolved"),0)+IFERROR(0,0) -> 0
A29: TOTAL | B29: =COUNTA('🔴 Risks'!A6:A500) -> 14 | C29: =COUNTA('🟡 Actions'!A6:A500) -> 17 | D29: =COUNTA('🟠 Issues'!A6:A500) -> 11 | E29: =COUNTA('🔵 Decisions'!A6:A500) -> 12 | F29: =COUNTA('🔴 Risks'!A6:A500)+COUNTA('🟡 Actions'!A6:A500)+COUNTA('🟠 Issues'!A6:A500)+COUNTA('🔵 Decisions'!A6:A500) -> 54

Sheet 🔴 Risks
A1: I-PROPERTY PROJECT RAID LOG · RISKS
A2: Risks that could negatively impact project delivery, scope, budget, or product outcomes if they occur · Source: BRD v1.3 · PRD v2.0 · SRS v3.0
A5: Risk ID | B5: Category | C5: Risk Description | D5: Source Doc | E5: Probability (1–5) | F5: Impact (1–5) | G5: Risk Score (P×I) | H5: Risk Level | I5: Current Status | J5: Owner | K5: Mitigation Strategy | L5: Contingency Plan | M5: Review Date | N5: Residual Risk
A6: R-01 | B6: Integration | C6: Oracle Financial API specification unavailable or incomplete by Sprint 1 — prevents development of payment automation feature, the primary Finance ROI driver | D6: PRD §10 / SRS §7 | E6: 4 | F6: 5 | G6: =E6*F6 -> 20 | J6: IT Director | K6: Begin OF integration scoping in Sprint 1 Week 1. Request API documentation and test environment credentials formally from OF vendor immediately after project kickoff. | L6: If API documentation not received by Sprint 1 Week 2: escalate to CFO. Contingency: deliver payment summary as OF-formatted Excel export for Phase 1; API integration becomes Phase 1b deliverable. | M6: May 2025 | N6: High
A7: R-02 | B7: Adoption | C7: Low user adoption — Operations and Finance teams revert to email and paper processes alongside the new system, resulting in dual-system operation with zero ROI | D7: PRD §10 | E7: 3 | F7: 5 | G7: =E7*F7 -> 15 | J7: VP Property Operations | K7: Mandatory directive from VP Operations: all new requests via I-Property from Day 1 of go-live. Include field officers and ABH representatives from all three California regions in UAT. Dedicated change management budget ($25K–$35K). | L7: Appoint regional champions from each area before go-live. If adoption <70% at Day 30 post-launch: escalate to CFO with remediation plan including executive enforcement. | M7: Jun 2025 | N7: Medium
A8: R-03 | B8: Data Migration | C8: Existing landlord and property profiles not migrated before go-live — users cannot submit requests and the system cannot be used for live transactions at launch | D8: PRD §10 / BRD §6.1 | E8: 4 | F8: 4 | G8: =E8*F8 -> 16 | J8: Director of Operations | K8: Data migration is a parallel workstream starting Month 1, not a pre-launch activity. Define minimum viable data set for go-live by Month 2. Build bulk import tool into Phase 1. | L8: If migration <80% complete at UAT entry: limit go-live to new agreements only (paper agreements migrated post-launch within 30 days). Full portfolio migration required before Month 9 review. | M8: May 2025 | N8: Medium
A9: R-04 | B9: Technical | C9: LDAP/SSO integration not available for UAT — authentication cannot be tested, blocking UAT and go-live timeline | D9: SRS §4.2 / PRD §7 | E9: 2 | F9: 5 | G9: =E9*F9 -> 10 | J9: IT Director | K9: Request LDAP test credentials and connectivity confirmation from IT Infrastructure by Sprint 1 Week 4. Schedule technical validation session with IT Infra in Week 2. | L9: If LDAP unavailable by Sprint 3: implement temporary local authentication for UAT only. Disable before production deployment. Document exception and get CFO sign-off. | M9: May 2025 | N9: Low
A10: R-05 | B10: Compliance | C10: California tax regulation changes (Sindh Sales Tax equivalent — California BOE commercial property tax) require system updates post-launch, temporarily compromising payment accuracy | D10: PRD §11 / SRS §7 | E10: 3 | F10: 4 | G10: =E10*F10 -> 12 | J10: Director of Finance + IT | K10: Tax rate configuration is System Admin-editable — no IT deployment required for standard rate changes. Annual compliance review scheduled each January. Finance Director monitors CA BOE announcements. | L10: Finance Director notifies IT within 5 business days of any regulatory change. IT updates configuration within 2 business days. Audit log captures all tax rate changes with timestamps. | M10: Jan 2026 | N10: Medium
A11: R-06 | B11: Financial | C11: Finance discovers payment export fields are incompatible with Oracle Financial import format — requiring rework after report design is complete | D11: PRD §10 / SRS §7.3 | E11: 3 | F11: 4 | G11: =E11*F11 -> 12 | J11: Finance Director + IT | K11: Obtain OF import field specification from Finance and IT before report design begins (Sprint 2). Validate format with Finance in Sprint 3 before full export development. | L11: If incompatibility discovered in UAT: extend UAT by 2 weeks for field mapping correction. Finance Director to sign off on export format before Sprint 4 development begins. | M11: May 2025 | N11: Low
A12: R-07 | B12: Schedule | C12: Key project stakeholder departure (Product Owner or Finance Director) during implementation — decision authority gap stalls approvals and UAT sign-off | D12: PRD §10 | E12: 2 | F12: 4 | G12: =E12*F12 -> 8 | J12: PMO Lead | K12: Identify succession stakeholder for each key role before Sprint 1. All decisions documented in project system — institutional knowledge in documentation, not individuals. | L12: If Product Owner departs: CFO assumes interim Product Owner role until replacement appointed. If Finance Director departs: Senior Finance Manager steps up with CFO oversight. | M12: Ongoing | N12: Low
A13: R-08 | B13: Technical | C13: Document storage infrastructure not provisioned before UAT — file upload features cannot be tested, blocking the document management and audit trail features | D13: SRS §4.1 / BRD §6.1 | E13: 2 | F13: 4 | G13: =E13*F13 -> 8 | J13: IT Infrastructure | K13: Infrastructure provisioning is a Sprint 1 Week 4 milestone. Document store configuration included in DP-001 as a go-live dependency checklist item. | L13: If storage not available for UAT: conduct UAT without file upload testing; schedule storage-specific UAT sprint after infrastructure is ready. Do not go-live without this capability. | M13: May 2025 | N13: Low
A14: R-09 | B14: Scope | C14: SLA threshold values not agreed by business before Sprint 3 — NE-14 SLA breach notifications cannot be configured, shipping without this management escalation capability | D14: SRS §11 / PRD §6 | E14: 3 | F14: 2 | G14: =E14*F14 -> 6 | J14: VP Property Operations | K14: Schedule SLA threshold workshop with ABH and Admin teams in Month 2 (Sprint 2). Block UAT sign-off on notification module until thresholds are confirmed and configured. | L14: If thresholds not agreed by Sprint 3: ship NE-14 with placeholder values (24h per stage) that can be reconfigured by System Admin post-launch without redeployment. | M14: May 2025 | N14: Low
A15: R-10 | B15: Quality | C15: Notification email templates not delivered by business before Sprint 3 — notification engine ships with placeholder content requiring rework and re-UAT | D15: SRS §11 / BRD §6.1.9 | E15: 3 | F15: 3 | G15: =E15*F15 -> 9 | J15: VP Property Operations | K15: Schedule notification template workshop with business team in Month 2. Templates are a Sprint 3 start dependency. Block UAT sign-off on notifications until all 14 templates are confirmed. | L15: If templates delayed past Sprint 3: notification system coded with clearly marked placeholders. Business team reviews and approves all templates before UAT Week 1, not before development. | M15: May 2025 | N15: Low
A16: R-11 | B16: Security | C16: Oracle Financial API key exposure risk — if API credentials are mishandled during development or testing, it could expose Meridian's financial system to unauthorized access | D16: SRS §7.3 | E16: 2 | F16: 5 | G16: =E16*F16 -> 10 | J16: IT Director | K16: API keys stored in server-side environment variables only — never in source code, client-side code, or application logs. Rotate all credentials between UAT and production. Penetration test before go-live. | L16: If credential exposure suspected: immediately rotate OF API key, audit OF transaction logs for unauthorized activity, notify Finance Director and Legal within 1 hour. | M16: Jun 2025 | N16: Low
A17: R-12 | B17: Technical | C17: Concurrent user load (100 users) causes system degradation — page load times exceed 3-second NFR threshold, impacting ABH and Finance workflow during month-end peak | D17: SRS §10 / NFR-01 | E17: 2 | F17: 3 | G17: =E17*F17 -> 6 | J17: IT Director | K17: Load test with 100 virtual users (JMeter) in UAT environment before go-live. Architecture designed for horizontal scaling (stateless app tier). DB connection pool configured min 10, max 50. | L17: If load test fails: scale app tier before go-live (horizontal scaling, no code change required per NFR-09). If persistent: defer non-critical report features to Phase 2 to reduce peak load. | M17: Jun 2025 | N17: Low
... A19: R-14 | B19: Vendor | C19: Oracle Financial experiences unplanned downtime during Meridian's monthly payment cycle — Finance cannot process payments, creating cash flow disruption | D19: PRD §5 / SRS §7.3 | E19: 1 | F19: 5 | G19: =E19*F19 -> 5 | J19: Finance Director + IT | K19: I-Property generates and stores approved payment batch regardless of OF availability. Retry policy: 3 attempts at 10-minute intervals with exponential backoff. System Admin alerted on all retry failures. | L19: If OF down at month-end: Finance Director notified immediately. Payment batch held in I-Property with approved status. Finance processes manually in OF once restored using I-Property export. Maximum 48-hour deferral acceptable. | M19: Monthly | N19: Low

Sheet 🟡 Actions
A1: I-PROPERTY PROJECT RAID LOG · ACTIONS
A2: Actions required to deliver the project, resolve risks/issues, or fulfill commitments made in BRD, PRD, and SRS · Source: BRD v1.3 · PRD v2.0 · SRS v3.0
A5: Action ID | B5: Category | C5: Action Description | D5: Source / Trigger | E5: Owner | F5: Assigned To | G5: Priority | H5: Status | I5: Due Date | J5: Completion Date | K5: Outcome / Notes | L5: BRD Ref | M5: SRS Ref
A6: A-01 | B6: Integration | C6: Obtain Oracle Financial API specification document and request test environment access from OF vendor | D6: Risk R-01 / PRD M-02 | E6: IT Director | F6: IT Integration Lead | I6: 30-Apr-2025 | K6: Blocking Sprint 4 development start. Must be escalated to CFO if not received by Sprint 1 Week 2. | L6: §6 Integration | M6: SRS §7.3
A7: A-02 | B7: Integration | C7: Validate Oracle Financial payment export field mapping against OF import specification before Sprint 4 development begins | D7: Risk R-06 / SRS §7.3 | E7: Finance Director | F7: Finance Systems Analyst | I7: 15-May-2025 | K7: Finance Director must sign off on field mapping document. No Sprint 4 payment work begins without this approval. | L7: §6.1.8 | M7: SRS §7.3
A8: A-03 | B8: Infrastructure | C8: Provision application server, database server, and document storage for development and UAT environments | D8: Risk R-08 / PRD M-02 | E8: IT Director | F8: IT Infrastructure Lead | I8: 30-Apr-2025 | K8: Must be complete before Sprint 1 ends. Development cannot begin without environments. Confirm with IT Infra weekly. | L8: §5 Constraints | M8: SRS §4.1
A9: A-04 | B9: Authentication | C9: Confirm LDAP/SSO connectivity from application server and obtain test credentials for authentication development | D9: Risk R-04 / SRS §4.2 | E9: IT Director | F9: IT Infrastructure Lead | I9: 30-Apr-2025 | K9: Required before Sprint 2 authentication development begins. If unavailable: document temporary local auth fallback procedure. | L9: §5 Constraints | M9: SRS §4.2
A10: A-05 | B10: Data Migration | C10: Define minimum viable landlord and property data set required for UAT go-live; assign data migration workstream owner | D10: Risk R-03 / PRD M-03 | E10: Director of Operations | F10: Operations Data Lead | I10: 08-May-2025 | K10: Data migration must be a parallel workstream from Month 1 — not a pre-launch sprint. Bulk import tool to be built into Phase 1 scope. | L10: §6 Assumptions | M10: SRS §9
A11: A-06 | B11: Data Migration | C11: Create landlord and property profile data import templates; distribute to Area Operations teams for data collection | D11: Risk R-03 | E11: Director of Operations | F11: Operations Data Lead | I11: 15-May-2025 | K11: Templates must match I-Property field definitions in SRS §9. QA review of template before distribution. | L11: §6 Assumptions | M11: SRS §9.3
A12: A-07 | B12: Business Requirements | C12: Conduct notification email template workshop with business team; produce and approve all 14 notification templates before Sprint 3 | D12: Risk R-10 / SRS §11 | E12: VP Property Operations | F12: Business Analyst | I12: 22-May-2025 | K12: All 14 NE-ID templates (TPL-01 through TPL-14) must be approved before notification engine development begins. Workshop scheduled for Month 2. | L12: §6.1.11 | M12: SRS §11
A13: A-08 | B13: Business Requirements | C13: Agree and document SLA threshold values for each approval stage (ABH, Director, Admin HO) with business stakeholders | D13: Risk R-09 / SRS §10 | E13: VP Property Operations | F13: Business Analyst | I13: 22-May-2025 | K13: SLA thresholds configure NE-14 breach alerts. Must be agreed before Sprint 3. Default placeholder: 24h per stage pending agreement. | L13: §6.1.9 | M13: SRS §10
A14: A-09 | B14: Legal | C14: Obtain Legal Director approval of lease agreement print templates for use in I-Property Print Queue feature | D14: Risk R-13 / BRD §6.1.4 | E14: Director of Legal | F14: Legal Counsel | I14: 15-Jun-2025 | K14: Templates required before Sprint 5 Print Queue UAT. Legal Director is sole approver. Escalate to CFO if approval delayed beyond Sprint 5 start. | L14: §6.1.4 | M14: SRS §8
A15: A-10 | B15: Architecture | C15: Complete Software Architecture Document (SAD-001) covering technology stack, deployment model, authentication design, and integration architecture | D15: PRD §1 Related Docs | E15: IT Director | F15: Solution Architect | I15: 30-Apr-2025 | K15: SAD-001 is a pre-development dependency. No Sprint 1 development begins without architecture decisions confirmed. | L15: All sections | M15: SRS §4
A16: A-11 | B16: Design | C16: Complete UI/UX Design Specification (UI-001) covering all 13 screens, wireframes, component library, and interaction patterns | D16: PRD §1 Related Docs | E16: Product Owner | F16: UX Lead | I16: 30-May-2025 | K16: UI-001 must be complete before frontend development of any screen begins. Review with each persona role group during design phase. | L16: All sections | M16: SRS §8
A17: A-12 | B17: Security | C17: Conduct pre-production penetration test covering authentication, RBAC, data encryption, and API security | D17: SRS §10 NFR-03/04/05 | E17: IT Director | F17: External Security Consultant | I17: 01-Jul-2025 | K17: Required before production go-live. Must cover: JWT token security, RBAC enforcement, TLS configuration, bank_account_no masking, audit log integrity. | L17: §6.2 | M17: SRS §10
... A22: A-17 | B22: Post-Launch | C22: Schedule 90-day post-launch review against PRD Section 9 success metrics; prepare measurement instrumentation before go-live | D22: PRD §9 | E22: Product Owner | F22: Business Analyst + IT | I22: 01-Nov-2025 | K22: Measurement framework must be in place at launch, not after. Metrics: cycle time, duplicate payments, Finance verification time, adoption rate, audit evidence time. | L22: All sections | M22: SRS §9

Sheet 🟠 Issues
A1: I-PROPERTY PROJECT RAID LOG · ISSUES
A2: Issues are problems that have already occurred or are currently affecting the project — requiring immediate action or management decision · Source: BRD v1.3 · PRD v2.0 · SRS v3.0
A5: Issue ID | B5: Category | C5: Issue Description | D5: Source / How Identified | E5: Impact | F5: Severity | G5: Status | H5: Owner | I5: Date Raised | J5: Target Resolution | K5: Resolution / Outcome | L5: BRD Ref | M5: SRS Ref
A6: ISS-01 | B6: Requirements | C6: BRD v1.3 stakeholder table has all contact names and email fields blank — roles are defined but individuals are not named, preventing notification routing and ownership assignment | D6: Identified during BRD review / SRS preparation | E6: Cannot assign individual ownership to approval roles. Notification email targets cannot be configured. RBAC user provisioning blocked. | H6: Product Owner | I6: 01-Apr-2025 | J6: 14-Apr-2025 | K6: Product Owner to collect names and email addresses for all 7 stakeholder roles. System Admin to provision LDAP accounts. Deadline: Sprint 1 Week 2. | L6: §3 Stakeholders | M6: SRS §3.2
A7: ISS-02 | B7: Requirements | C7: BRD v1.3 states 'Events list for notification generation and Report formats will be shared by business' (§6.1.11) but this has not been delivered — SRS v3.0 has been written with assumptions | D7: BRD §6.1.11 / PRD §13 | E7: Notification templates (14 events) and report format specifications are based on BA assumptions, not confirmed business requirements. Risk of rework during UAT. | H7: VP Property Operations | I7: 01-Apr-2025 | J7: 22-May-2025 | K7: Business to review and formally approve all 14 notification templates (SRS §11) and all report formats (SRS §5.5) before Sprint 3. See Action A-07. | L7: §6.1.11 | M7: SRS §11
A8: ISS-03 | B8: Requirements | C8: BRD v1.3 and SRS v3.0 both reference the process flow diagram placeholder ('Process Flow diagram would be here') — no actual workflow diagrams exist yet | D8: BRD §6.1.7 / SRS §6 | E8: Development team cannot build the workflow engine without confirmed sequence diagrams. SDD-001 cannot be started without workflow diagrams. | H8: Business Analyst | I8: 01-Apr-2025 | J8: 30-Apr-2025 | K8: BA to produce formal workflow diagrams (BPMN or equivalent) for all 4 primary flows: New Request, Renewal, Vacated, Utility Bill. Must be reviewed and signed off by Product Owner before SDD-001 begins. | L8: §6.1.7 | M8: SRS §6
A9: ISS-04 | B9: Scope | C9: BRD v1.3 §6.1.5 includes Signage Payment module in the main requirements body despite also being listed as Phase 2 — creates scope ambiguity for development team | D9: BRD §6.1.5 vs §2.1 | E9: Development team may build signage features in Phase 1 unless scope is explicitly clarified. Risk of over-delivery and schedule overrun. | H9: Product Owner | I9: 01-Apr-2025 | J9: 14-Apr-2025 | K9: Product Owner to issue formal scope clarification: Signage module (F-19) is Phase 2 only. SRS v3.0 FR-SG-01 to FR-SG-04 are Phase 2. Remove from Phase 1 sprint planning immediately. | L9: §2.1 / §6.1.5 | M9: SRS §5.5
A10: ISS-05 | B10: Integration | C10: Oracle Financial integration specification (IDD-001) has not been started — all SRS §7 API contracts for OF endpoints are based on assumed field mappings, not confirmed OF specifications | D10: SRS §7 / PRD §13 | E10: Payment batch transmission (INT-01), expense accrual (INT-03), and payment confirmation (INT-02) may require significant rework if OF field names, authentication, or payload structure differ from assumptions. | H10: IT Director | I10: 01-Apr-2025 | J10: 30-Apr-2025 | K10: IT Director to formally request OF API documentation this week. IDD-001 must be started within Sprint 1. All SRS §7 OF endpoint specifications to be validated against actual OF API before Sprint 4. See Action A-01 and A-02. | L10: §6 Assumptions | M10: SRS §7
A11: ISS-06 | B11: Document | C11: SRS v3.0 §5.1 (FR-NR-01 processing logic) references a 'working day calendar' for the month-end payment scheduler — no calendar configuration mechanism is specified or scoped | D11: SRS §5.5 / BRD §6.1.7 | E11: Payment summary will generate on incorrect dates if public holidays and non-working days are not accounted for. California has specific public holidays. | H11: IT Director | I11: 01-Apr-2025 | J11: 30-Apr-2025 | K11: Add working day calendar configuration to System Admin console scope (SCR-13 or new SCR-14). Finance Director to provide annual California working day calendar. IT to confirm whether this requires a new feature or a configuration file. | L11: §6 Assumptions | M11: SRS §5.5
A12: ISS-07 | B12: Budget | C12: Phase 1 investment range ($520K–$640K) in PRD §5.2 has not been formally approved by CFO — project has been scoped but investment authorization is pending | D12: PRD §14 / §5.2 | E12: Development cannot be formally commissioned without investment approval. Sprint 1 resourcing at risk. | H12: CFO | I12: 01-Apr-2025 | J12: 14-Apr-2025 | K12: PRD v2.0 submitted to CFO for review and investment authorization. Target: approval by April 14, 2025 to maintain Q3 2025 go-live timeline. See Action A-16. | L12: PRD §5.2 | M12: —
A13: ISS-08 | B13: Technical | C13: SRS v3.0 NFR-07 specifies IE11 minimum legacy support — however, IE11 was officially retired by Microsoft in June 2022 and is not supported by most modern JavaScript frameworks | D13: SRS §10 NFR-07 | E13: If the development team's chosen framework (React or equivalent) does not support IE11, this NFR cannot be met as written. Requires product decision. | H13: Product Owner + IT Director | I13: 01-Apr-2025 | J13: 22-Apr-2025 | K13: Product Owner to make a formal decision: retain IE11 support (requires polyfills and may limit framework choices) or descope IE11 and replace with 'last 3 versions of Edge, Chrome, Firefox' as the compatibility standard. Decision required before architecture is finalized. | L13: §6.2 | M13: SRS §10 NFR-07
A14: ISS-09 | B14: Compliance | C14: SRS v3.0 NFR-08 targets WCAG 2.1 AA accessibility — however, UI-001 has not been started and no UX designer has formally committed to this standard | D14: SRS §10 NFR-08 | E14: If accessibility is not designed into UI-001 from the start, retrofitting it post-design is expensive and time-consuming. | H14: UX Lead + Product Owner | I14: 01-Apr-2025 | J14: 30-May-2025 | K14: UX Lead to formally acknowledge WCAG 2.1 AA as a design constraint before UI-001 begins. Include accessibility review checkpoint after each UI-001 design sprint. Confirm whether automated accessibility testing tool (axe, Lighthouse) will be included in UAT test suite. | L14: §6.2 | M14: SRS §10 NFR-08
A15: ISS-10 | B15: Process | C15: No Change Request process has been defined for post-PRD scope changes — BRD and SRS changes are currently uncontrolled, creating version management risk | D15: PRD §14 | E15: Any uncontrolled scope change after executive approval could silently expand Phase 1 scope, delay go-live, and erode the investment ROI. | H15: PMO Lead | I15: 01-Apr-2025 | J15: 14-Apr-2025 | K15: PMO Lead to define and publish Change Request template and approval process by Sprint 1 Week 1. All changes to BRD v1.3, SRS v3.0, or PRD v2.0 scope after executive approval require formal CR with CFO and Product Owner sign-off. | L15: All sections | M15: All sections
A16: ISS-11 | B16: Data | C16: There is no data governance policy for I-Property specifying who owns landlord and property data, who can edit master records, and what the correction process is for financial data errors | D16: SRS §9 / BRD §6.1 | E16: Without a data governance policy, the system of record value of I-Property is undermined — multiple parties may edit data without a controlled process, reintroducing the errors the system is designed to eliminate. | H16: VP Property Operations | I16: 01-Apr-2025 | J16: 22-May-2025 | K16: VP Operations and Finance Director to produce a one-page I-Property Data Governance Policy covering: data ownership by entity, edit permissions by role, financial data correction process (including audit trail requirements), and data quality review cadence. Required before UAT. | L16: §6 Assumptions | M16: SRS §9

Sheet 🔵 Decisions
A1: I-PROPERTY PROJECT RAID LOG · DECISIONS
A2: Decisions required from project leadership or stakeholders — pending decisions create blockers; made decisions are recorded for audit and change management · Source: BRD v1.3 · PRD v2.0 · SRS v3.0
A5: Decision ID | B5: Category | C5: Decision Required / Made | D5: Source / Trigger | E5: Options Considered | F5: Decision Made | G5: Rationale | H5: Decision Owner | I5: Date Required | J5: Date Decided | K5: Impact if Not Decided | L5: BRD Ref | M5: SRS Ref
A6: D-01 | B6: Investment | C6: Formal investment approval for Phase 1 ($520K–$640K) and authorization to commence development | D6: PRD §5.2 / §14 | E6: A) Approve full Phase 1 scope; B) Approve Phase 1 with reduced scope (defer some Should Have features); C) Defer project | F6: PENDING DECISION | G6: Without approval, Sprint 1 resourcing and vendor contracts cannot be committed. Q3 2025 go-live timeline at risk if decision delayed past April 14. | H6: CFO | I6: 14-Apr-2025 | J6: — | K6: Project stalls. No development commences. Q3 2025 go-live impossible. | L6: PRD §5 | M6: —
A7: D-02 | B7: Architecture | C7: Technology stack selection for application layer and database — must be confirmed before SDD-001 and Sprint 1 development begin | D7: SRS §4.1 / SAD-001 | E7: A) Node.js + PostgreSQL; B) Java Spring + Oracle DB; C) .NET Core + SQL Server; D) Other | F7: PENDING — IT Director to decide | G7: Architecture decision drives developer hiring/allocation, framework selection, and Oracle Financial integration approach. Deadline: SAD-001 completion. | H7: IT Director | I7: 30-Apr-2025 | J7: — | K7: SDD-001 cannot be written. Sprint 1 development cannot begin. Architecture-dependent SRS sections remain unresolved. | L7: — | M7: SRS §4.1
A8: D-03 | B8: Scope | C8: Formal scope clarification: is Signage Payment module (BRD §6.1.5) in Phase 1 or Phase 2? | D8: BRD §6.1.5 / PRD §8 | E8: A) Include in Phase 1 (extends schedule ~4 weeks); B) Confirm as Phase 2 only (aligned with PRD v2.0) | F8: PENDING — Product Owner to decide | G8: BRD §6.1.5 includes signage in main requirements body, creating development team ambiguity. PRD v2.0 explicitly classifies as Phase 2 (F-19). Requires formal written clarification. | H8: Product Owner | I8: 14-Apr-2025 | J8: — | K8: Development team may include signage in Phase 1 sprint planning, creating uncontrolled scope expansion and schedule overrun. | L8: §6.1.5 | M8: SRS §5.5
A9: D-04 | B9: Technical | C9: IE11 compatibility decision: retain IE11 minimum support as stated in SRS NFR-07, or replace with 'last 3 versions of modern browsers only' | D9: SRS §10 NFR-07 / Issue ISS-08 | E9: A) Retain IE11 support (requires polyfills, limits framework choices, increases dev cost ~$15K–$25K); B) Descope IE11 — Chrome, Firefox, Edge last 3 versions only | F9: PENDING — Product Owner + IT Director | G9: Microsoft retired IE11 June 2022. Most modern JS frameworks do not support it. Retaining it constrains technology choices and adds significant testing overhead for <1% of modern enterprise browser usage. | H9: Product Owner + IT Director | I9: 22-Apr-2025 | J9: — | K9: Architecture and framework selection cannot be finalized. Development team cannot proceed with confidence on frontend stack. | L9: §6.2 | M9: SRS §10 NFR-07
A10: D-05 | B10: Integration | C10: Oracle Financial integration approach: real-time REST API vs. scheduled batch file transfer | D10: SRS §7.3 / IDD-001 | E10: A) REST API (real-time payment confirmation, lower latency, more complex); B) Batch file (simpler, proven, 24-hour payment confirmation lag); C) Hybrid (API for stop-payment alerts, batch for monthly summaries) | F10: PENDING — IT Director + Finance Director | G10: Decision impacts IDD-001 design, Sprint 4 development timeline, and Finance's real-time visibility into payment confirmations. OF vendor to advise on their preferred/supported integration pattern. | H10: IT Director + Finance Director | I10: 30-Apr-2025 | J10: — | K10: IDD-001 cannot be written. Sprint 4 OF integration development cannot begin. Finance payment workflow design incomplete. | L10: §6 Integration | M10: SRS §7.3
A11: D-06 | B11: Security | C11: Authentication architecture: OAuth 2.0 vs. SAML 2.0 for LDAP/SSO integration | D11: SRS §4.2 / SAD-001 | E11: A) OAuth 2.0 + OIDC (modern, REST-native, widely supported); B) SAML 2.0 (enterprise standard, Meridian's existing SSO may use this); C) Both (if Meridian uses multiple IdP systems) | F11: PENDING — IT Director | G11: Decision depends on Meridian's existing Identity Provider (Okta, Azure AD, or on-prem LDAP). IT Director to confirm with IT Infrastructure team. | H11: IT Director | I11: 30-Apr-2025 | J11: — | K11: Authentication development cannot begin. All user-facing features depend on this. LDAP connectivity confirmation (Action A-04) is a prerequisite for this decision. | L11: §5 Constraints | M11: SRS §4.2
A12: D-07 | B12: Product | C12: WCAG 2.1 AA accessibility commitment: formal confirmation that UI-001 will be designed to this standard | D12: SRS §10 NFR-08 / Issue ISS-09 | E12: A) Commit to WCAG 2.1 AA (recommended; increases design effort ~10–15%); B) Target WCAG 2.1 A only; C) No formal accessibility commitment in Phase 1 | F12: PENDING — Product Owner + UX Lead | G12: California Government Code §11546.7 applies to state entities; Meridian as a private company is subject to ADA Title III for public accommodations. Internal tools have more flexibility, but institutional investor due diligence increasingly includes accessibility. | H12: Product Owner | I12: 30-Apr-2025 | J12: — | K12: UX Lead cannot make design decisions without this commitment. Retrofitting accessibility post-design is 3–5× more expensive than designing for it from the start. | L12: §6.2 | M12: SRS §10 NFR-08
A13: D-08 | B13: Data | C13: Data governance policy: who can edit master landlord and property records, and what is the financial data correction process? | D13: Issue ISS-11 / SRS §9 | E13: A) Strict: only System Admin edits master records; B) Moderate: System Admin + authorized Operations managers; C) Open: any authorized role per RBAC | F13: PENDING — VP Operations + Finance Director | G13: Without this policy, the system of record value of I-Property is undermined. Financial data errors corrected without a controlled process reintroduce the audit gaps the system is designed to close. | H13: VP Property Operations + Finance Director | I13: 22-May-2025 | J13: — | K13: UAT cannot be signed off without data governance in place. Post-launch financial data quality is at risk. | L13: §6 Assumptions | M13: SRS §9
A14: D-09 | B14: Budget | C14: Phase 2 investment pre-approval: confirm that Phase 2 ($150K–$200K estimated) will be included in Q1 2026 budget planning | D14: PRD §5 / §12 | E14: A) Pre-approve Phase 2 in principle now (maintains momentum, no binding commitment); B) Defer Phase 2 budget decision to Month 9 review; C) Terminate after Phase 1 only | F14: PENDING — CFO | G14: Pre-approval in principle (not a commitment) allows the product team to begin Phase 2 requirements gathering during Phase 1 delivery, reducing total program timeline by 2–3 months. | H14: CFO | I14: 14-Apr-2025 | J14: — | K14: Phase 2 planning cannot begin. Mobile UI, signage module, and Capex integration will be delayed to Q2 2026 at earliest. | L14: PRD §2.3 | M14: —
A15: D-10 | B15: Compliance | C15: California CPRA (Consumer Privacy Rights Act) applicability: does I-Property's storage of landlord personal data (CNIC, bank details) require a CPRA compliance review? | D15: SRS §9 / PRD §5 | E15: A) Engage Legal for formal CPRA assessment before go-live; B) Determine landlord data is B2B and outside CPRA scope; C) Implement privacy-by-design measures as a precaution regardless of formal classification | F15: PENDING — Director of Legal | G15: California CPRA covers 'personal information' of California residents. Landlords who are individuals (not corporations) may qualify. Bank account numbers and CNIC equivalents are sensitive data under CPRA. Legal review is prudent before production deployment. | H15: Director of Legal | I15: 22-Apr-2025 | J15: — | K15: If I-Property goes live without a CPRA assessment and landlord data is later determined to be in scope, Meridian faces potential regulatory penalties and mandatory system remediation. | L15: §5 Constraints | M15: SRS §9
A16: D-11 | B16: Operations | C16: Go-live strategy: big-bang (all regions simultaneously) vs. phased rollout (pilot one region first) | D16: PRD §12 / Risk R-02 | E16: A) Big-bang: all 3 California regions (LA, Bay Area, San Diego) go live simultaneously — maximum impact, higher risk; B) Pilot LA region first (4–6 weeks), then remaining regions | F16: PENDING — VP Property Operations | G16: Phased rollout reduces adoption risk (R-02) and allows issues to be resolved before full deployment. However, it requires managing parallel systems (paper + I-Property) in non-pilot regions for 4–6 weeks. | H16: VP Property Operations | I16: 22-May-2025 | J16: — | K16: Go-live planning and training schedule cannot be finalized without this decision. Change management approach differs significantly between options. | L16: All sections | M16: —
A17: D-12 | B17: Reporting | C17: Report format specifications: business to confirm and approve all report formats (types, columns, filter options, export formats) before Sprint 5 development | D17: BRD §6.1.11 / SRS §5.5 | E17: A) Business delivers specifications by Sprint 3 (recommended); B) Business reviews BA-drafted specifications in SRS v3.0 and approves/amends; C) Reports designed by BA assumptions and reviewed in UAT | F17: PENDING — VP Operations + Finance Director | G17: BRD §6.1.11 states report formats will be provided by business but they have not been delivered. SRS v3.0 §5.5 contains BA-assumed specifications. Business confirmation required before Sprint 5. | H17: VP Property Operations + Finance Director | I17: 22-May-2025 | J17: — | K17: Report module development proceeds on BA assumptions. UAT rework required if business requires different formats, columns, or filters. | L17: §6.1.11 | M17: SRS §5.5

Sheet 📊 Risk Heat Map
A1: I-PROPERTY RISK HEAT MAP
A2: Probability vs Impact matrix for all identified project risks · Score = Probability (1–5) × Impact (1–5)
A5: RISK HEAT MAP — PROBABILITY × IMPACT
C6: Impact 1 Insignificant | D6: Impact 2 Minor | E6: Impact 3 Moderate | F6: Impact 4 Significant | G6: Impact 5 Catastrophic
A7: PROBABILITY → 5 (Almost Certain) to 1 (Rare) | B7: 5 — Almost Certain | C7: 5 | D7: 10 | E7: 15 | F7: 20 | G7: 25
B8: 4 — Likely | C8: 4 | D8: 8 | E8: 12 | F8: 16 R-03 | G8: 20 R-01
B9: 3 — Possible | C9: 3 | D9: 6 | E9: 9 R-09 R-10 | F9: 12 R-05 R-06 | G9: 15 R-02
B10: 2 — Unlikely | C10: 2 | D10: 4 | E10: 6 R-12 R-13 | F10: 8 R-07 R-08 | G10: 10 R-11
B11: 1 — Rare | C11: 1 | D11: 2 | E11: 3 | F11: 4 R-14 | G11: 5
B14: RISK LEVEL LEGEND
B15: Low Risk (Score 1–4)
B16: Medium Risk (Score 5–9)
B17: High Risk (Score 10–14)
B18: Critical Risk (Score 15–25)
